{
  "namedays": [
    {
      "date": "1/5",
      "names": [
        "Ιερεμίας",
        "Τάμαρα",
        "Ταμάρα",
        "Φιλόσοφος",
        "Σοφός",
        "Φιλοσοφία",
        "Φιλοσοφή",
        "Ισιδώρα",
        "Δώρα"
      ]
    },
    {
      "date": "2/5",
      "names": [
        "Έσπερος",
        "Εσπέρα",
        "Εσπερία",
        "Αυγερινός",
        "Αυγέρης",
        "Αυγίτης",
        "Αυγέρας",
        "Αυγέρου",
        "Αυγερού",
        "Μπόρις",
        "Μπόρισος",
        "Ματρώνα",
        "Ματρόνα"
      ]
    },
    {
      "date": "3/5",
      "names": ["Μαύρος", "Μαύρα", "Μαυρούλα", "Μαυρίτσα", "Ροδόπη", "Ροδώπη"]
    },
    {
      "date": "4/5",
      "names": [
        "Πελαγής",
        "Πελάγιος",
        "Πελαγία",
        "Πελαγούλα",
        "Πελαγίνα",
        "Πελαγίτσα",
        "Πελαγιώ",
        "Ιλάριος",
        "Μελής",
        "Μέλος",
        "Μέλιος",
        "Μέλας",
        "Μέλια",
        "Μελίτσα"
      ]
    },
    {
      "date": "5/5",
      "names": [
        "Ειρηναίος",
        "Ρένος",
        "Ειρηναία",
        "Ευφραίμ",
        "Ευφραίμιος",
        "Ευφραίμης",
        "Εφραίμ",
        "Ευφραιμία",
        "Ευφραιμίτσα",
        "Ειρήνη",
        "Ρένα",
        "Ρήνα",
        "Ρηνιώ",
        "Ρηνούλα",
        "Ειρήνα",
        "Ειρήνγκω",
        "Ρένια"
      ]
    },
    {
      "date": "6/5",
      "names": [
        "Σεραφείμ",
        "Σεραφειμία",
        "Σεραφείμα",
        "Σεραφίνα",
        "Σεραφειμή",
        "Σεραφειμούλα",
        "Σεραφειμίτσα",
        "Ιώβ",
        "Ιωβία",
        "Ιώβη"
      ]
    },
    {
      "date": "7/5",
      "names": []
    },
    {
      "date": "8/5",
      "names": [
        "Θεολόγος",
        "Θεολόγης",
        "Θολόγος",
        "Θολόγης",
        "Θολόης",
        "Θεολογία",
        "Θολογία",
        "Μήλιος",
        "Μήλης",
        "Μηλιώ",
        "Μηλιά",
        "Μηλίτσα",
        "Αρσένιος",
        "Αρσένης",
        "Αρσενία",
        "Αρσίνα",
        "Αρσινόη"
      ]
    },
    {
      "date": "9/5",
      "names": [
        "Χριστόφορος",
        "Χριστοφόρης",
        "Φόρης",
        "Χριστόφης",
        "Χριστοφία",
        "Χριστοφίνα",
        "Ησαΐας"
      ]
    },
    {
      "date": "10/5",
      "names": [
        "Σίμωνας",
        "Σίμων",
        "Σίμος",
        "Σιμώνα",
        "Σιμόνα",
        "Σιμωνία",
        "Σιμώνη",
        "Σιμωνίτσα"
      ]
    },
    {
      "date": "11/5",
      "names": [
        "Αρμόδιος",
        "Αρμόδης",
        "Μεθόδιος",
        "Αργύρης",
        "Αργύριος",
        "Αργυρή",
        "Αργυρούλα",
        "Ρούλα",
        "Αργυρώ",
        "Ασημίνα",
        "Ολυμπιάς",
        "Ολυμπία",
        "Ολυμπιάδα",
        "Ολύμπω",
        "Ολύμπη",
        "Όλια",
        "Ολυμπούλα",
        "Διοσκουρίδης",
        "Διοσκορίδης",
        "Διόσκορος"
      ]
    },
    {
      "date": "12/5",
      "names": [
        "Επιφάνειος",
        "Επιφάνιος",
        "Επιφανία",
        "Θεόδωρος",
        "Θοδωρής",
        "Θόδωρος",
        "Θεοδώρα",
        "Δώρα",
        "Θοδώρα",
        "Δωρούλα",
        "Ντόρα"
      ]
    },
    {
      "date": "13/5",
      "names": ["Γλυκερία", "Σέργιος", "Σεργία", "Σεργιανή", "Σεργιούλα"]
    },
    {
      "date": "14/5",
      "names": [
        "Αριστοτέλης",
        "Τέλης",
        "Θεράπων",
        "Ισίδωρος",
        "Σιδέρης",
        "Ισιδώρα",
        "Δώρα"
      ]
    },
    {
      "date": "15/5",
      "names": [
        "Αχίλλιος",
        "Αχιλλέας",
        "Αχίλιος",
        "Αχίλειος",
        "Αχίλλειος",
        "Παχώμιος",
        "Παχούμιος",
        "Πάχος",
        "Καλή",
        "Κάλη"
      ]
    },
    {
      "date": "16/5",
      "names": []
    },
    {
      "date": "17/5",
      "names": [
        "Ανδρόνικος",
        "Ανδρονίκη",
        "Ιουνία",
        "Γιουνία",
        "Σόλων",
        "Σόλωνας",
        "Σολόχων"
      ]
    },
    {
      "date": "18/5",
      "names": [
        "Ιούλιος",
        "Ιουλία",
        "Ιουλιανή",
        "Ιουλίτσα",
        "Γιουλία",
        "Γιούλα",
        "Γιουλίτσα",
        "Τζούλια",
        "Γιούλη",
        "Γαλάτεια",
        "Γαλατία",
        "Φαεινός",
        "Φαεινή"
      ]
    },
    {
      "date": "19/5",
      "names": [
        "Πατρίκιος",
        "Πάτρικ",
        "Πατρίκος",
        "Πατρίκης",
        "Πατρίτσιος",
        "Πατρίτσης",
        "Πατρικία",
        "Πατρίκα",
        "Πατριτσία",
        "Πατρίτσα",
        "Θεόγνωστος",
        "Θεογνώστης",
        "Θεογνώσιος",
        "Θεογνωσία",
        "Θεόκτιστος",
        "Μένανδρος",
        "Μαριλένα",
        "Μαγδαληνή",
        "Μάγδα",
        "Μαγδούλα",
        "Μαγδαλένα",
        "Μαγδαλένια",
        "Μαγδαλή",
        "Μαγδάλω"
      ]
    },
    {
      "date": "20/5",
      "names": ["Θαλλελαίος", "Θαλής", "Λυδία", "Λήδα", "Λύδα"]
    },
    {
      "date": "21/5",
      "names": [
        "Κωνσταντίνος",
        "Κώστας",
        "Κωστής",
        "Κωσταντίνος",
        "Κωστάκης",
        "Κωνσταντίνα",
        "Κωνσταντία",
        "Κωσταντίνα",
        "Κωστούλα",
        "Ντίνα",
        "Νάντια",
        "Ελένη",
        "Έλενα",
        "Ελεάννα",
        "Ελεάνα",
        "Λένα",
        "Λενίτσα",
        "Λένγκω",
        "Λενιώ",
        "Ελεονόρα",
        "Ελεονώρα",
        "Νόρα",
        "Μαριλένα",
        "Ελενάκι",
        "Νίτσα"
      ]
    },
    {
      "date": "22/5",
      "names": [
        "Αιμίλιος",
        "Μίλιος",
        "Αιμιλία",
        "Έμυ",
        "Εμιλία",
        "Έμιλυ",
        "Έμμα",
        "Μίλια",
        "Κόδρος",
        "Κόδρα"
      ]
    },
    {
      "date": "23/5",
      "names": []
    },
    {
      "date": "24/5",
      "names": [
        "Παλλαδία",
        "Παλαδία",
        "Παλλάδα",
        "Παλάδα",
        "Μαρκιανή",
        "Μαρκιάνα",
        "Χριστιανός",
        "Χριστιανή",
        "Φωτεινή",
        "Φώτω",
        "Φώφη",
        "Φωτούλα",
        "Φαίη",
        "Φωφώ"
      ]
    },
    {
      "date": "25/5",
      "names": []
    },
    {
      "date": "26/5",
      "names": ["Αλφαίος", "Συνέσιος", "Συνέσης", "Συνεσία", "Καρπός"]
    },
    {
      "date": "27/5",
      "names": ["Αλύπιος", "Αλυπία", "Θεράπων"]
    },
    {
      "date": "28/5",
      "names": [
        "Διοσκουρίδης",
        "Διοσκορίδης",
        "Διόσκορος",
        "Δημήτριος",
        "Δημήτρης",
        "Μήτρος"
      ]
    },
    {
      "date": "29/5",
      "names": [
        "Θεοδοσία",
        "Θεοδόσω",
        "Υπομονή",
        "Ολιβιανός",
        "Ολβιανός",
        "Ολιβία",
        "Ολίβια"
      ]
    },
    {
      "date": "30/5",
      "names": ["Εμμέλεια"]
    },
    {
      "date": "31/5",
      "names": ["Ερμείας", "Ερμειάς", "Ερμεία", "Μάγος", "Μάγια"]
    }
  ]
}
